nbdev_template/__init__.py
nbdev_template/_nbdev.py
nbdev_template/inventory.py
villaInventorySdk/__init__.py
villaInventorySdk/_nbdev.py
villaInventorySdk/inventory.py
villaInventorySdk/price.py
villaInventorySdk-0.1.6.dist-info/LICENSE
villaInventorySdk-0.1.6.dist-info/METADATA
villaInventorySdk-0.1.6.dist-info/WHEEL
villaInventorySdk-0.1.6.dist-info/entry_points.txt
villaInventorySdk-0.1.6.dist-info/top_level.txt
villaInventorySdk-0.1.6.dist-info/RECORD
